AUTHORS
ChangeLog
README.rst
requirements.txt
setup.cfg
setup.py
alignak/__init__.py
alignak/modules/__init__.py
alignak/modules/mod_surveil_config/__init__.py
alignak/modules/mod_surveil_config/module.py
alignak_mod_surveil_config.egg-info/PKG-INFO
alignak_mod_surveil_config.egg-info/SOURCES.txt
alignak_mod_surveil_config.egg-info/dependency_links.txt
alignak_mod_surveil_config.egg-info/namespace_packages.txt
alignak_mod_surveil_config.egg-info/not-zip-safe
alignak_mod_surveil_config.egg-info/requires.txt
alignak_mod_surveil_config.egg-info/top_level.txt
doc/Makefile
doc/make.bat
doc/source/conf.py
doc/source/index.rst
etc/alignak/modules/mod-surveil-config.cfg