Metadata-Version: 1.0
Name: alignak-mod-surveil-config
Version: 0.1.0
Summary: Alignak module load config from Surveil API
Home-page: UNKNOWN
Author: Alexandre Viau
Author-email: alexandre.viau@savoirfairelinux.com
License: GNU Affero General Public License
Platform: UNKNOWN
